amor_eos-3.0.6.dist-info/licenses/LICENSE
eos/__init__.py
eos/__main__.py
eos/command_line.py
eos/const.py
eos/e2h.py
eos/event_analysis.py
eos/event_data_types.py
eos/event_handling.py
eos/file_reader.py
eos/header.py
eos/helpers.py
eos/helpers_fallback.py
eos/helpers_numba.py
eos/instrument.py
eos/kafka_events.py
eos/kafka_serializer.py
eos/logconfig.py
eos/nicos.py
eos/normalization.py
eos/options.py
eos/path_handling.py
eos/projection.py
eos/reduction_e2h.py
eos/reduction_kafka.py
eos/reduction_reflectivity.py
amor_eos-3.0.6.dist-info/METADATA
amor_eos-3.0.6.dist-info/WHEEL
amor_eos-3.0.6.dist-info/entry_points.txt
amor_eos-3.0.6.dist-info/top_level.txt
amor_eos-3.0.6.dist-info/RECORD
