Metadata-Version: 2.4
Name: amor_eos
Version: 3.0.6
Summary: EOS reflectometry reduction for AMOR instrument
Author: Jochen Stahn - Paul Scherrer Institut
Author-email: jochen.stahn@psi.ch
License: MIT
Classifier: Programming Language :: Python :: 3
Classifier: License :: OSI Approved :: MIT License
Classifier: Operating System :: OS Independent
Classifier: Topic :: Scientific/Engineering
Classifier: Development Status :: 5 - Production/Stable
Requires-Python: >=3.8
License-File: LICENSE
Requires-Dist: numpy
Requires-Dist: h5py
Requires-Dist: orsopy
Requires-Dist: numba
Requires-Dist: backports.strenum; python_version < "3.11"
Requires-Dist: backports.zoneinfo; python_version < "3.9"
Dynamic: license-file
